formatic/__init__.py
formatic/__main__.py
formatic/cli.py
formatic/defaults.py
formatic/injection_engine.py
formatic/utils.py
formatic/version.py
formatic/harnesses/__init__.py
formatic/harnesses/abstract_injection_harness.py
formatic/harnesses/subprocess_injection_harness.py
formatic/walkers/__init__.py
formatic/walkers/abstract_injection_walker.py
formatic/walkers/attribute_injection_walker.py
formatic/walkers/class_injection_walker.py
formatic/walkers/code_object_field_injection_walker.py
formatic/walkers/code_object_injection_walker.py
formatic/walkers/doc_string_injection_walker.py
formatic/walkers/failed_injection_walker.py
formatic/walkers/function_injection_walker.py
formatic/walkers/module_injection_walker.py
formatic/walkers/name_injection_walker.py
formatic-0.0.1.dist-info/LICENSE.txt
formatic-0.0.1.dist-info/METADATA
formatic-0.0.1.dist-info/WHEEL
formatic-0.0.1.dist-info/entry_points.txt
formatic-0.0.1.dist-info/top_level.txt
formatic-0.0.1.dist-info/RECORD
