Metadata-Version: 2.1
Name: formatic
Version: 0.0.1
Summary: automated traversal of format() string injections
Home-page: https://github.com/welchbj/formatic
Author: Brian Welch
Author-email: welch18@vt.edu
License: MIT
Platform: UNKNOWN
Classifier: License :: OSI Approved :: MIT License
Classifier: Environment :: Console
Classifier: Development Status :: 3 - Alpha
Classifier: Programming Language :: Python :: 3.6
Classifier: Programming Language :: Python :: Implementation :: CPython
Classifier: Topic :: Security
Classifier: Topic :: Utilities
Requires-Dist: colorama
Requires-Dist: pygments
Requires-Dist: uncompyle6
Requires-Dist: xdis
